metallaxis/MetallaxisGui.ui
metallaxis/MetallaxisProgress.ui
metallaxis/MetallaxisSettings.ui
metallaxis/SVGClasses.py
metallaxis/__init__.py
metallaxis/__main__.py
metallaxis/annotation/SnpSift.jar
metallaxis/annotation/snpEff.config
metallaxis/annotation/snpEff.jar
Metallaxis-0.9.dist-info/LICENSE
Metallaxis-0.9.dist-info/METADATA
Metallaxis-0.9.dist-info/WHEEL
Metallaxis-0.9.dist-info/top_level.txt
Metallaxis-0.9.dist-info/RECORD
