Metadata-Version: 2.1
Name: Metallaxis
Version: 0.9
Summary: A graphical python-based VCF viewer with optional annotation
Home-page: https://github.com/SL-LAIDLAW/Metallaxis
Author: Sean Laidlaw
Author-email: seanlaidlaw95@gmail.com
License: GPLv3
Platform: UNKNOWN
Classifier: License :: OSI Approved :: GNU General Public License v3 (GPLv3)
Classifier: Development Status :: 4 - Beta
Classifier: Operating System :: OS Independent
Classifier: Programming Language :: Python :: 3.6
Classifier: Topic :: Scientific/Engineering :: Bio-Informatics
Requires-Dist: python-magic
Requires-Dist: pandas
Requires-Dist: numpy
Requires-Dist: PyQt5
Requires-Dist: requests
Requires-Dist: wget
Requires-Dist: matplotlib
